{
  "coverage": {
    "./contracts/ExampleToken.cdc": {
      "line_hits": {
        "101": 1,
        "102": 1,
        "104": 1,
        "108": 1,
        "112": 5,
        "117": 0,
        "118": 0,
        "119": 0,
        "123": 0,
        "128": 0,
        "142": 7,
        "143": 7,
        "156": 6,
        "157": 6,
        "158": 6,
        "159": 6,
        "17": 1,
        "170": 0,
        "185": 1,
        "186": 1,
        "187": 1,
        "199": 9,
        "203": 4,
        "205": 4,
        "209": 4,
        "215": 4,
        "216": 4,
        "217": 4,
        "218": 4,
        "220": 4,
        "222": 4,
        "223": 4,
        "26": 47,
        "28": 2,
        "33": 4,
        "39": 4,
        "40": 4,
        "51": 40,
        "58": 3,
        "62": 0,
        "66": 1,
        "92": 21,
        "93": 21,
        "94": 21,
        "95": 21,
        "96": 21
      },
      "missed_lines": [
        62,
        117,
        118,
        119,
        123,
        128,
        170
      ],
      "statements": 46,
      "percentage": "84.8%"
    },
    "./contracts/FungibleToken.cdc": {
      "line_hits": {
        "100": 7,
        "148": 1,
        "151": 1,
        "153": 0,
        "163": 0,
        "164": 0,
        "168": 0,
        "174": 0,
        "182": 8,
        "186": 7,
        "190": 15,
        "201": 6,
        "203": 6,
        "206": 18,
        "215": 0,
        "224": 9,
        "225": 9,
        "98": 7
      },
      "missed_lines": [
        153,
        163,
        164,
        168,
        174,
        215
      ],
      "statements": 18,
      "percentage": "66.7%"
    },
    "./contracts/FungibleTokenMetadataViews.cdc": {
      "line_hits": {
        "102": 2,
        "103": 2,
        "104": 2,
        "107": 0,
        "145": 40,
        "146": 40,
        "148": 40,
        "149": 40,
        "150": 40,
        "151": 40,
        "152": 40,
        "153": 40,
        "163": 0,
        "164": 0,
        "165": 0,
        "168": 0,
        "176": 0,
        "27": 2,
        "28": 2,
        "38": 2,
        "39": 2,
        "40": 2,
        "42": 0,
        "87": 5,
        "88": 5,
        "89": 5,
        "90": 5,
        "91": 5,
        "92": 5
      },
      "missed_lines": [
        42,
        107,
        163,
        164,
        165,
        168,
        176
      ],
      "statements": 29,
      "percentage": "75.9%"
    },
    "./contracts/FungibleTokenSwitchboard.cdc": {
      "line_hits": {
        "102": 0,
        "104": 0,
        "107": 0,
        "110": 0,
        "138": 0,
        "140": 0,
        "143": 0,
        "164": 1,
        "167": 1,
        "168": 1,
        "172": 1,
        "174": 1,
        "176": 1,
        "195": 1,
        "198": 1,
        "201": 1,
        "215": 4,
        "219": 3,
        "222": 3,
        "239": 0,
        "242": 0,
        "244": 0,
        "248": 0,
        "249": 0,
        "254": 0,
        "256": 0,
        "257": 0,
        "266": 1,
        "267": 0,
        "270": 1,
        "282": 1,
        "283": 0,
        "286": 1,
        "297": 0,
        "298": 0,
        "299": 0,
        "300": 0,
        "303": 0,
        "314": 0,
        "316": 0,
        "317": 0,
        "319": 0,
        "322": 0,
        "330": 4,
        "331": 4,
        "332": 2,
        "333": 2,
        "336": 4,
        "342": 0,
        "343": 0,
        "344": 0,
        "345": 0,
        "350": 1,
        "359": 1,
        "363": 1,
        "364": 1,
        "365": 1,
        "68": 1,
        "71": 1,
        "74": 1,
        "77": 1,
        "82": 0,
        "94": 0,
        "97": 0,
        "98": 0
      },
      "missed_lines": [
        82,
        94,
        97,
        98,
        102,
        104,
        107,
        110,
        138,
        140,
        143,
        239,
        242,
        244,
        248,
        249,
        254,
        256,
        257,
        267,
        283,
        297,
        298,
        299,
        300,
        303,
        314,
        316,
        317,
        319,
        322,
        342,
        343,
        344,
        345
      ],
      "statements": 65,
      "percentage": "46.2%"
    },
    "./contracts/utility/Burner.cdc": {
      "line_hits": {
        "24": 1,
        "25": 1,
        "26": 1,
        "27": 0,
        "28": 0,
        "29": 0,
        "30": 0,
        "32": 0,
        "33": 0,
        "34": 0,
        "35": 0,
        "36": 0,
        "37": 0,
        "39": 0,
        "41": 0
      },
      "missed_lines": [
        27,
        28,
        29,
        30,
        32,
        33,
        34,
        35,
        36,
        37,
        39,
        41
      ],
      "statements": 15,
      "percentage": "20.0%"
    },
    "./contracts/utility/MetadataViews.cdc": {
      "line_hits": {
        "111": 0,
        "112": 0,
        "121": 0,
        "122": 0,
        "125": 0,
        "143": 5,
        "144": 5,
        "156": 5,
        "166": 0,
        "167": 0,
        "168": 0,
        "171": 0,
        "181": 0,
        "191": 0,
        "192": 0,
        "193": 0,
        "196": 0,
        "208": 10,
        "218": 0,
        "219": 0,
        "220": 0,
        "223": 0,
        "257": 0,
        "259": 0,
        "260": 0,
        "261": 0,
        "276": 0,
        "277": 0,
        "278": 0,
        "280": 0,
        "282": 0,
        "290": 0,
        "300": 0,
        "301": 0,
        "302": 0,
        "305": 0,
        "315": 0,
        "340": 0,
        "341": 0,
        "342": 0,
        "343": 0,
        "354": 0,
        "362": 0,
        "372": 0,
        "373": 0,
        "374": 0,
        "377": 0,
        "392": 0,
        "393": 0,
        "394": 0,
        "398": 0,
        "399": 0,
        "400": 0,
        "401": 0,
        "404": 0,
        "432": 0,
        "433": 0,
        "435": 0,
        "436": 0,
        "437": 0,
        "450": 0,
        "460": 0,
        "461": 0,
        "462": 0,
        "465": 0,
        "478": 0,
        "48": 0,
        "488": 0,
        "489": 0,
        "49": 0,
        "490": 0,
        "493": 0,
        "50": 0,
        "513": 0,
        "514": 0,
        "517": 0,
        "518": 0,
        "519": 0,
        "529": 0,
        "530": 0,
        "531": 0,
        "534": 0,
        "561": 0,
        "562": 0,
        "563": 0,
        "564": 0,
        "565": 0,
        "566": 0,
        "567": 0,
        "568": 0,
        "579": 0,
        "580": 0,
        "581": 0,
        "584": 0,
        "60": 0,
        "61": 0,
        "62": 0,
        "627": 0,
        "629": 0,
        "630": 0,
        "631": 0,
        "632": 0,
        "633": 0,
        "643": 0,
        "644": 0,
        "645": 0,
        "648": 0,
        "65": 0,
        "683": 0,
        "684": 0,
        "685": 0,
        "686": 0,
        "687": 0,
        "688": 0,
        "699": 0,
        "700": 0,
        "701": 0,
        "704": 0,
        "81": 5,
        "85": 3
      },
      "missed_lines": [
        48,
        49,
        50,
        60,
        61,
        62,
        65,
        111,
        112,
        121,
        122,
        125,
        166,
        167,
        168,
        171,
        181,
        191,
        192,
        193,
        196,
        218,
        219,
        220,
        223,
        257,
        259,
        260,
        261,
        276,
        277,
        278,
        280,
        282,
        290,
        300,
        301,
        302,
        305,
        315,
        340,
        341,
        342,
        343,
        354,
        362,
        372,
        373,
        374,
        377,
        392,
        393,
        394,
        398,
        399,
        400,
        401,
        404,
        432,
        433,
        435,
        436,
        437,
        450,
        460,
        461,
        462,
        465,
        478,
        488,
        489,
        490,
        493,
        513,
        514,
        517,
        518,
        519,
        529,
        530,
        531,
        534,
        561,
        562,
        563,
        564,
        565,
        566,
        567,
        568,
        579,
        580,
        581,
        584,
        627,
        629,
        630,
        631,
        632,
        633,
        643,
        644,
        645,
        648,
        683,
        684,
        685,
        686,
        687,
        688,
        699,
        700,
        701,
        704
      ],
      "statements": 120,
      "percentage": "5.0%"
    },
    "./contracts/utility/PrivateReceiverForwarder.cdc": {
      "line_hits": {
        "35": 1,
        "37": 1,
        "39": 1,
        "41": 1,
        "43": 1,
        "48": 2,
        "50": 2,
        "57": 2,
        "64": 1,
        "66": 1,
        "70": 1,
        "77": 1,
        "79": 1,
        "80": 1,
        "82": 1
      },
      "missed_lines": [],
      "statements": 15,
      "percentage": "100.0%"
    },
    "./contracts/utility/TokenForwarding.cdc": {
      "line_hits": {
        "105": 0,
        "106": 0,
        "107": 0,
        "108": 0,
        "113": 1,
        "115": 1,
        "122": 1,
        "52": 1,
        "54": 1,
        "56": 1,
        "58": 1,
        "60": 1,
        "66": 0,
        "76": 0,
        "83": 0,
        "85": 0,
        "93": 0,
        "94": 0,
        "96": 0,
        "97": 0,
        "98": 0,
        "99": 0
      },
      "missed_lines": [
        66,
        76,
        83,
        85,
        93,
        94,
        96,
        97,
        98,
        99,
        105,
        106,
        107,
        108
      ],
      "statements": 22,
      "percentage": "36.4%"
    }
  },
  "excluded_locations": [
    "A.0000000000000003.FlowToken",
    "A.0000000000000004.FlowFees",
    "A.0000000000000002.FungibleTokenSwitchboard",
    "A.0000000000000001.FlowStakingCollection",
    "A.0000000000000001.MetadataViews",
    "A.0000000000000001.FlowServiceAccount",
    "A.0000000000000001.NonFungibleToken",
    "A.0000000000000001.EVM",
    "A.0000000000000002.FungibleToken",
    "A.0000000000000001.ViewResolver",
    "I.Crypto",
    "s.7465737400000000000000000000000000000000000000000000000000000000",
    "A.0000000000000001.LockedTokens",
    "A.0000000000000001.FlowDKG",
    "A.0000000000000001.FlowEpoch",
    "A.0000000000000001.ExampleNFT",
    "I.Test",
    "I.BlockchainHelpers",
    "A.0000000000000001.FlowStorageFees",
    "A.0000000000000001.FlowIDTableStaking",
    "A.0000000000000002.FungibleTokenMetadataViews",
    "A.0000000000000001.FlowClusterQC",
    "A.0000000000000001.NodeVersionBeacon",
    "A.0000000000000001.RandomBeaconHistory",
    "A.0000000000000001.StakingProxy"
  ]
}