{
  "coverage": {
    "A.0000000000000007.ExampleToken": {
      "line_hits": {
        "101": 1,
        "115": 6,
        "117": 1,
        "122": 2,
        "128": 2,
        "129": 2,
        "140": 2,
        "149": 1,
        "153": 0,
        "155": 1,
        "167": 3,
        "178": 1,
        "179": 1,
        "187": 1,
        "188": 1,
        "207": 1,
        "208": 1,
        "210": 1,
        "211": 1,
        "212": 1,
        "213": 1,
        "217": 1,
        "233": 1,
        "234": 1,
        "235": 1,
        "236": 1,
        "241": 2,
        "242": 2,
        "243": 2,
        "244": 2,
        "245": 2,
        "248": 2,
        "249": 2,
        "253": 2,
        "260": 2,
        "265": 2,
        "266": 2,
        "269": 2,
        "54": 12,
        "68": 6,
        "69": 6,
        "70": 6,
        "82": 5,
        "83": 5,
        "84": 5,
        "85": 5,
        "86": 5,
        "90": 7,
        "91": 1
      },
      "missed_lines": [
        153
      ],
      "statements": 49,
      "percentage": "98.0%"
    },
    "A.0000000000000007.FungibleTokenMetadataViews": {
      "line_hits": {
        "101": 1,
        "102": 1,
        "103": 1,
        "106": 0,
        "154": 2,
        "155": 2,
        "156": 2,
        "158": 2,
        "159": 2,
        "160": 2,
        "161": 2,
        "162": 2,
        "163": 2,
        "164": 2,
        "165": 2,
        "175": 1,
        "176": 1,
        "177": 1,
        "180": 0,
        "188": 0,
        "26": 1,
        "27": 1,
        "37": 1,
        "38": 1,
        "39": 1,
        "41": 0,
        "86": 2,
        "87": 2,
        "88": 2,
        "89": 2,
        "90": 2,
        "91": 2
      },
      "missed_lines": [
        41,
        106,
        180,
        188
      ],
      "statements": 32,
      "percentage": "87.5%"
    },
    "A.0000000000000007.FungibleTokenSwitchboard": {
      "line_hits": {
        "102": 0,
        "105": 0,
        "108": 0,
        "111": 0,
        "137": 0,
        "139": 0,
        "142": 0,
        "161": 1,
        "164": 1,
        "165": 1,
        "170": 1,
        "174": 1,
        "177": 1,
        "194": 1,
        "197": 1,
        "200": 1,
        "212": 4,
        "216": 3,
        "219": 3,
        "236": 0,
        "240": 0,
        "243": 0,
        "247": 0,
        "248": 0,
        "250": 0,
        "252": 0,
        "253": 0,
        "262": 1,
        "263": 0,
        "266": 1,
        "278": 1,
        "279": 0,
        "282": 1,
        "293": 4,
        "294": 4,
        "295": 2,
        "296": 2,
        "299": 4,
        "310": 0,
        "312": 0,
        "313": 0,
        "315": 0,
        "319": 0,
        "327": 4,
        "328": 4,
        "329": 4,
        "330": 2,
        "332": 4,
        "337": 1,
        "346": 1,
        "350": 1,
        "351": 1,
        "352": 1,
        "68": 1,
        "71": 1,
        "74": 1,
        "77": 1,
        "82": 0,
        "94": 0,
        "97": 0,
        "98": 0
      },
      "missed_lines": [
        82,
        94,
        97,
        98,
        102,
        105,
        108,
        111,
        137,
        139,
        142,
        236,
        240,
        243,
        247,
        248,
        250,
        252,
        253,
        263,
        279,
        310,
        312,
        313,
        315,
        319
      ],
      "statements": 61,
      "percentage": "57.4%"
    },
    "A.0000000000000007.TokenForwarding": {
      "line_hits": {
        "102": 1,
        "104": 1,
        "111": 1,
        "52": 1,
        "54": 1,
        "56": 1,
        "58": 1,
        "64": 0,
        "74": 0,
        "81": 0,
        "83": 0,
        "91": 0,
        "92": 0,
        "94": 0,
        "95": 0,
        "96": 0,
        "97": 0
      },
      "missed_lines": [
        64,
        74,
        81,
        83,
        91,
        92,
        94,
        95,
        96,
        97
      ],
      "statements": 17,
      "percentage": "41.2%"
    }
  },
  "excluded_locations": [
    "A.0000000000000002.FungibleToken",
    "A.0000000000000002.FungibleTokenMetadataViews",
    "A.0000000000000001.FlowClusterQC",
    "A.0000000000000001.FlowIDTableStaking",
    "A.0000000000000001.NFTStorefront",
    "I.Crypto",
    "A.0000000000000001.NodeVersionBeacon",
    "A.0000000000000001.FlowServiceAccount",
    "A.0000000000000001.FlowDKG",
    "A.0000000000000001.LockedTokens",
    "A.0000000000000001.FlowStakingCollection",
    "A.0000000000000001.ExampleNFT",
    "I.Test",
    "A.0000000000000001.StakingProxy",
    "A.0000000000000004.FlowFees",
    "A.0000000000000001.FlowStorageFees",
    "A.0000000000000001.FlowEpoch",
    "A.0000000000000001.NFTStorefrontV2",
    "s.7465737400000000000000000000000000000000000000000000000000000000",
    "A.0000000000000003.FlowToken",
    "A.0000000000000001.ViewResolver",
    "A.0000000000000001.MetadataViews",
    "A.0000000000000001.NonFungibleToken"
  ]
}